Pruebas/src/program_counter.sv
// program_counter.sv
// PC de 4 bits con incremento, carga y reset asíncrono

module program_counter (
    input  logic        clk,
    input  logic        rst,      // reset asíncrono activo en alto
    input  logic        load,
    input  logic [3:0]  next_pc,
    output logic [3:0]  pc
);

    always_ff @(posedge clk or posedge rst) begin
        if (rst)
            pc <= 4'd0;
        else if (load)
            pc <= next_pc;
        else
            pc <= pc + 4'd1;
    end

endmodule

`ifndef NO_PC_TB
// =============================================================
// Testbench auto-verificable (>=10 ciclos) para program_counter
// =============================================================
module tb_program_counter;
    logic clk;
    logic rst;
    logic load;
    logic [3:0] next_pc;
    logic [3:0] pc;

    program_counter dut (.*);

    // Reloj: periodo 10 ns
    initial begin
        clk = 1'b0;
        forever #5 clk = ~clk;
    end

    // VCD opcional: ejecutar con "+dump"
    initial begin
        if ($test$plusargs("dump")) begin
            $dumpfile("tb_program_counter.vcd");
            $dumpvars(0, tb_program_counter);
        end
    end

    // Estímulos y comprobaciones
    initial begin : stimulus
        integer i;
        $display("Ciclo | RST | LOAD | NEXT_PC |  PC ");
        $display("------|-----|------|---------|-----");

        // 1) Reset asíncrono
    rst = 1; load = 0; next_pc = 4'd0;
    repeat (2) @(posedge clk);
    @(negedge clk); rst = 0; #1; // desactivar lejos del posedge para evitar carreras
    if (pc !== 4'd0) $fatal(1, "Fallo: pc tras reset != 0 (pc=%0d)", pc);

        // 2) 5 incrementos (>= 5 ciclos)
    for (i = 0; i < 5; i = i + 1) @(posedge clk);
    #1; // esperar a que se apliquen las NBAs
    if (pc !== 4'd5) $fatal(1, "Fallo: pc tras 5 incrementos != 5 (pc=%0d)", pc);

        // 3) load = 1 -> cargar 10
    load = 1; next_pc = 4'd10; @(posedge clk); #1;
    if (pc !== 4'd10) $fatal(1, "Fallo: load no cargó 10 (pc=%0d)", pc);
        load = 0;

        // 4) 3 incrementos desde 10 -> 13
    repeat (3) @(posedge clk);
    #1;
    if (pc !== 4'd13) $fatal(1, "Fallo: pc tras 3 incrementos desde 10 != 13 (pc=%0d)", pc);

        // 5) Forzar 15 y verificar overflow 15->0
    load = 1; next_pc = 4'd15; @(posedge clk); #1;
    if (pc !== 4'd15) $fatal(1, "Fallo: load no cargó 15 (pc=%0d)", pc);
    load = 0; @(posedge clk); #1;
    if (pc !== 4'd0) $fatal(1, "Fallo: overflow 15->0 no ocurrió (pc=%0d)", pc);

        $display("OK: Simulación completada (>=10 ciclos, reset, incremento, load y overflow verificados).");
        $finish;
    end
endmodule
`endif

Pruebas/src/ram16x8.sv
// ram16x8.sv
// Memoria RAM 16x8 (4 bits de dirección, 8 bits por palabra)
// - Lectura/escritura síncronas al flanco positivo de clk
// - Inicializada con valores de ejemplo 0x41..0x50 ("A"..)

module ram16x8 (
    input  logic        clk,
    input  logic        we,
    input  logic [3:0]  addr,
    input  logic [7:0]  data_in,
    output logic [7:0]  data_out
);
    logic [7:0] mem [0:15];

    // Inicialización con valores ASCII: 0x41 ('A') + índice
    initial begin : init_mem
        integer i;
        for (i = 0; i < 16; i++) begin
            mem[i] = 8'h41 + i; // A, B, C, ...
        end
    end

    always_ff @(posedge clk) begin
        if (we)
            mem[addr] <= data_in;
        data_out <= mem[addr];
    end
endmodule

// =============================================================
// Testbench: RAM 16x8 con acceso mediante el PC de 4 bits
// Requisitos verificados:
//  - Lectura secuencial pc->addr con datos de ejemplo
//  - Efecto de escritura (we=1) en un ciclo
//  - Comportamiento al llegar pc=1111 (wrap a 0000)
//  - Tabla de resultados por ciclo (pc, addr, data_out)
// =============================================================
module tb_ram16x8;
    // Señales PC
    logic clk;
    logic rst;
    logic load;
    logic [3:0] next_pc;
    logic [3:0] pc;

    // Señales RAM
    logic        we;
    logic [3:0]  addr;
    logic [7:0]  data_in;
    logic [7:0]  data_out;

    // Instancias
    program_counter u_pc (
        .clk(clk), .rst(rst), .load(load), .next_pc(next_pc), .pc(pc)
    );
    ram16x8 u_ram (
        .clk(clk), .we(we), .addr(addr), .data_in(data_in), .data_out(data_out)
    );

    // Reloj 10 ns
    initial begin
        clk = 1'b0;
        forever #5 clk = ~clk;
    end

    // VCD opcional
    initial begin
        if ($test$plusargs("dump")) begin
            $dumpfile("tb_ram16x8.vcd");
            $dumpvars(0, tb_ram16x8);
        end
    end

    // Estímulos, tabla y CSV
    initial begin : stim
        integer cycle;
        integer csv;
        byte ascii;
        // CSV: abrir archivo
        csv = $fopen("tb_ram16x8.csv", "w");
        if (csv == 0) $fatal(1, "No se pudo abrir tb_ram16x8.csv para escritura");
        $fdisplay(csv, "cycle,pc,addr,data_out_hex,data_out_dec,data_out_ascii");

        $display("Ciclo | PC  | ADDR | DATA_OUT (hex) | ASCII");
        $display("------|-----|------|----------------|------");

        // Reset y arranque del PC
        rst = 1; load = 0; next_pc = 4'd0; we = 0; data_in = 8'h00; addr = 4'd0;
        repeat (2) @(posedge clk);
        @(negedge clk) rst = 0; #1;

        // Leer 20 ciclos, con una escritura en un ciclo específico
        for (cycle = 1; cycle <= 20; cycle = cycle + 1) begin
            // Dirección conectada al PC
            addr = pc;

            // Inyectar una escritura en el ciclo 2 (visible nuevamente tras wrap)
            if (cycle == 2) begin
                we = 1; data_in = 8'h5A; // 'Z'
            end else begin
                we = 0; data_in = 8'h00;
            end

            @(posedge clk); #1; // esperar NBAs

            // Mostrar fila de tabla y volcar a CSV
            ascii = (data_out>=8'h20 && data_out<=8'h7E) ? data_out : 8'h2E; // '.' si no imprimible
            $display("%5d | %04b | %04b |      0x%02h       |  %c",
                     cycle, pc, addr, data_out, ascii);
            $fdisplay(csv, "%0d,%04b,%04b,0x%02h,%0d,%c", cycle, pc, addr, data_out, data_out, ascii);
        end

        $display("\nNota: En el ciclo 2 se escribió 'Z' (0x5A) en la dirección indicada por PC (addr=0001).");
    $display("Al retornar el PC a esa dirección tras el wrap (ciclo 18), se observa el nuevo dato.");
        $display("Cuando el PC llega a 1111, al siguiente ciclo vuelve a 0000 (lectura circular).\n");
        $display("CSV generado: tb_ram16x8.csv");
        $fclose(csv);
        $finish;
    end
endmodule

Pruebas/tb_ram16x8.vcd
$date
	Wed Nov 05 15:47:51 2025
$end
$version
	Icarus Verilog
$end
$timescale
	1s
$end
$scope module tb_ram16x8 $end
$var wire 4 ! pc [3:0] $end
$var wire 8 " data_out [7:0] $end
$var reg 4 # addr [3:0] $end
$var reg 1 $ clk $end
$var reg 8 % data_in [7:0] $end
$var reg 1 & load $end
$var reg 4 ' next_pc [3:0] $end
$var reg 1 ( rst $end
$var reg 1 ) we $end
$scope module u_pc $end
$var wire 1 $ clk $end
$var wire 1 & load $end
$var wire 4 * next_pc [3:0] $end
$var wire 1 ( rst $end
$var reg 4 + pc [3:0] $end
$upscope $end
$scope module u_ram $end
$var wire 4 , addr [3:0] $end
$var wire 1 $ clk $end
$var wire 8 - data_in [7:0] $end
$var wire 1 ) we $end
$var reg 8 . data_out [7:0] $end
$scope begin init_mem $end
$var integer 32 / i [31:0] $end
$upscope $end
$upscope $end
$scope begin stim $end
$var reg 8 0 ascii [7:0] $end
$var integer 32 1 csv [31:0] $end
$var integer 32 2 cycle [31:0] $end
$upscope $end
$upscope $end
$enddefinitions $end
$comment Show the parameter values. $end
$dumpall
$end
#0
$dumpvars
bx 2
b10000000000000000000000000000011 1
b0 0
b10000 /
bx .
b0 -
b0 ,
b0 +
b0 *
0)
1(
b0 '
0&
b0 %
0$
b0 #
bx "
b0 !
$end
#5
b1000001 "
b1000001 .
1$
#10
0$
#15
1$
#20
0(
0$
#21
b1 2
#25
b1 !
b1 +
1$
#26
b1011010 %
b1011010 -
1)
b1 #
b1 ,
b10 2
b1000001 0
#30
0$
#35
b10 !
b10 +
b1000010 "
b1000010 .
1$
#36
b0 %
b0 -
0)
b10 #
b10 ,
b11 2
b1000010 0
#40
0$
#45
b11 !
b11 +
b1000011 "
b1000011 .
1$
#46
b11 #
b11 ,
b100 2
b1000011 0
#50
0$
#55
b100 !
b100 +
b1000100 "
b1000100 .
1$
#56
b100 #
b100 ,
b101 2
b1000100 0
#60
0$
#65
b101 !
b101 +
b1000101 "
b1000101 .
1$
#66
b101 #
b101 ,
b110 2
b1000101 0
#70
0$
#75
b110 !
b110 +
b1000110 "
b1000110 .
1$
#76
b110 #
b110 ,
b111 2
b1000110 0
#80
0$
#85
b111 !
b111 +
b1000111 "
b1000111 .
1$
#86
b111 #
b111 ,
b1000 2
b1000111 0
#90
0$
#95
b1000 !
b1000 +
b1001000 "
b1001000 .
1$
#96
b1000 #
b1000 ,
b1001 2
b1001000 0
#100
0$
#105
b1001 !
b1001 +
b1001001 "
b1001001 .
1$
#106
b1001 #
b1001 ,
b1010 2
b1001001 0
#110
0$
#115
b1010 !
b1010 +
b1001010 "
b1001010 .
1$
#116
b1010 #
b1010 ,
b1011 2
b1001010 0
#120
0$
#125
b1011 !
b1011 +
b1001011 "
b1001011 .
1$
#126
b1011 #
b1011 ,
b1100 2
b1001011 0
#130
0$
#135
b1100 !
b1100 +
b1001100 "
b1001100 .
1$
#136
b1100 #
b1100 ,
b1101 2
b1001100 0
#140
0$
#145
b1101 !
b1101 +
b1001101 "
b1001101 .
1$
#146
b1101 #
b1101 ,
b1110 2
b1001101 0
#150
0$
#155
b1110 !
b1110 +
b1001110 "
b1001110 .
1$
#156
b1110 #
b1110 ,
b1111 2
b1001110 0
#160
0$
#165
b1111 !
b1111 +
b1001111 "
b1001111 .
1$
#166
b1111 #
b1111 ,
b10000 2
b1001111 0
#170
0$
#175
b0 !
b0 +
b1010000 "
b1010000 .
1$
#176
b0 #
b0 ,
b10001 2
b1010000 0
#180
0$
#185
b1 !
b1 +
b1000001 "
b1000001 .
1$
#186
b1 #
b1 ,
b10010 2
b1000001 0
#190
0$
#195
b10 !
b10 +
b1011010 "
b1011010 .
1$
#196
b10 #
b10 ,
b10011 2
b1011010 0
#200
0$
#205
b11 !
b11 +
b1000011 "
b1000011 .
1$
#206
b11 #
b11 ,
b10100 2
b1000011 0
#210
0$
#215
b100 !
b100 +
b1000100 "
b1000100 .
1$
#216
b10101 2
b1000100 0
